geko/__init__.py
geko/anomalous_dimensions.py
geko/op.py
geko-0.1.1.dist-info/LICENSE
geko-0.1.1.dist-info/METADATA
geko-0.1.1.dist-info/WHEEL
geko-0.1.1.dist-info/RECORD
