Metadata-Version: 2.3
Name: geko
Version: 0.1.1
Summary: (Point-like) Photon Evolution Kernel Object
License: GPL-3
Author: Felix Hekhorn
Author-email: felix.a.hekhorn@jyu.fi
Requires-Python: >=3.9,<3.13
Classifier: License :: Other/Proprietary License
Classifier: Programming Language :: Python :: 3
Classifier: Programming Language :: Python :: 3.9
Classifier: Programming Language :: Python :: 3.10
Classifier: Programming Language :: Python :: 3.11
Classifier: Programming Language :: Python :: 3.12
Requires-Dist: eko[box] (==0.14.6)
Requires-Dist: numpy (<2.0.0)
Requires-Dist: scipy (<2.0.0)
